CHANGES.txt
LICENSE.txt
MANIFEST.in
README.rst
setup.py
mw_aiohttp_security/__init__.py
mw_aiohttp_security/auth.py
mw_aiohttp_security.egg-info/PKG-INFO
mw_aiohttp_security.egg-info/SOURCES.txt
mw_aiohttp_security.egg-info/dependency_links.txt
mw_aiohttp_security.egg-info/requires.txt
mw_aiohttp_security.egg-info/top_level.txt